[
  {
    "id": "officer-1",
    "name": "HAmssa Hossam",
    "position": "Secretary",
    "image": "officers/1.jpeg",
    "bio": "",
    "email": "",
    "linkedin": ""
  },
  {
    "id": "officer-2",
    "name": "Mohamed El Azazy",
    "position": "Treasurer",
    "image": "officers/2.jpg",
    "bio": "",
    "email": "",
    "linkedin": ""
  },
  {
    "id": "officer-3",
    "name": "Tasbeeh Mahmoud",
    "position": "Founder & ChairPerson",
    "image": "officers/3.jpeg",
    "bio": "",
    "email": "",
    "linkedin": ""
  },
  {
    "id": "officer-4",
    "name": "Zahy Adel",
    "position": "Vice ChairPerson",
    "image": "officers/4.jpeg",
    "bio": "",
    "email": "",
    "linkedin": ""
  }
]
